tumblr_backup/__init__.py
tumblr_backup/__main__.py
tumblr_backup/is_reblog.py
tumblr_backup/logging.py
tumblr_backup/login.py
tumblr_backup/main.py
tumblr_backup/note_scraper.py
tumblr_backup/util.py
tumblr_backup/wget.py
tumblr_backup/assets/npf2html.iife.js
tumblr_backup/assets/npf2html.iife.js.map
tumblr_backup/npf/models.py
tumblr_backup/npf/render.py
tumblr_backup-1.6.0.dist-info/licenses/LICENSE
tumblr_backup-1.6.0.dist-info/licenses/3rdparty/npf2html/LICENSE
tumblr_backup-1.6.0.dist-info/METADATA
tumblr_backup-1.6.0.dist-info/WHEEL
tumblr_backup-1.6.0.dist-info/entry_points.txt
tumblr_backup-1.6.0.dist-info/top_level.txt
tumblr_backup-1.6.0.dist-info/RECORD
