Metadata-Version: 2.4
Name: tumblr-backup
Version: 1.6.0
Summary: An advanced tool for backing up Tumblr blogs.
License-Expression: GPL-3.0-only
Project-URL: Homepage, https://github.com/cebtenzzre/tumblr-utils
Project-URL: Bug Reports, https://github.com/cebtenzzre/tumblr-utils/issues
Project-URL: Source, https://github.com/cebtenzzre/tumblr-utils
Classifier: Programming Language :: Python :: 3
Classifier: Programming Language :: Python :: 3 :: Only
Classifier: Programming Language :: Python :: 3.10
Classifier: Programming Language :: Python :: 3.11
Classifier: Programming Language :: Python :: 3.12
Classifier: Programming Language :: Python :: 3.13
Requires-Python: >=3.10
License-File: LICENSE
License-File: 3rdparty/npf2html/LICENSE
Requires-Dist: colorama<0.5,>=0.4.6
Requires-Dist: filetype~=1.2
Requires-Dist: platformdirs~=4.2
Requires-Dist: pydantic<3,>=2.12.3
Requires-Dist: requests<3,>=2.32.5
Requires-Dist: typing_extensions<5,>=4.5.0
Requires-Dist: urllib3<2.6,>=2.2.2
Provides-Extra: bs4
Requires-Dist: beautifulsoup4<5,>=4.14.2; extra == "bs4"
Requires-Dist: lxml<6.1,>=6.0.2; extra == "bs4"
Provides-Extra: dash
Requires-Dist: quickjs<2,>=1.19.4; extra == "dash"
Provides-Extra: exif
Requires-Dist: py3exiv2~=0.12; extra == "exif"
Provides-Extra: jq
Requires-Dist: jq~=1.6; extra == "jq"
Provides-Extra: video
Requires-Dist: yt_dlp>=2023.12.30; extra == "video"
Provides-Extra: all
Requires-Dist: tumblr-backup[bs4,dash,exif,jq,video]; extra == "all"
Provides-Extra: dev
Requires-Dist: tumblr-backup[all]; extra == "dev"
Requires-Dist: flake8==7.3.0; extra == "dev"
Requires-Dist: mypy==1.18.2; extra == "dev"
Requires-Dist: wemake-python-styleguide==1.4.0; extra == "dev"
Requires-Dist: mini-racer>=0.12.4; extra == "dev"
Requires-Dist: pysocks<2,>=1.7.1; extra == "dev"
Requires-Dist: types-lxml==2025.08.25; extra == "dev"
Requires-Dist: types-requests<3,>=2.32.4.20250913; extra == "dev"
Requires-Dist: youtube_dl>=2021.12.17; extra == "dev"
Dynamic: license-file
